ha_py_trello-0.24.1.dist-info/licenses/AUTHORS.md
ha_py_trello-0.24.1.dist-info/licenses/LICENSE
test/__init__.py
test/test_board.py
test/test_card.py
test/test_checklist.py
test/test_trello_client.py
trello/__init__.py
trello/__main__.py
trello/attachments.py
trello/base.py
trello/board.py
trello/card.py
trello/checklist.py
trello/compat.py
trello/customfield.py
trello/exceptions.py
trello/label.py
trello/member.py
trello/organization.py
trello/powerup.py
trello/star.py
trello/trelloclient.py
trello/trellolist.py
trello/util.py
trello/webhook.py
trello/batch/__init__.py
trello/batch/batcherror.py
trello/batch/batchresponse.py
trello/batch/board.py
ha_py_trello-0.24.1.dist-info/METADATA
ha_py_trello-0.24.1.dist-info/WHEEL
ha_py_trello-0.24.1.dist-info/top_level.txt
ha_py_trello-0.24.1.dist-info/RECORD
