Metadata-Version: 2.4
Name: ha-py-trello
Version: 0.24.1
Summary: Python wrapper around the Trello API (Home Assistant specific)
Home-page: https://github.com/ScottG489/ha-py-trello
Download-URL: https://github.com/ScottG489/ha-py-trello
Author: Scott Giminiani (originally Richard Kolkovich)
Author-email: scottg489@gmail.com
License: BSD License
Keywords: python
Classifier: Development Status :: 4 - Beta
Classifier: Intended Audience :: Developers
Classifier: License :: OSI Approved :: BSD License
Classifier: Operating System :: OS Independent
Classifier: Programming Language :: Python
Classifier: Programming Language :: Python :: 2
Classifier: Programming Language :: Python :: 2.7
Classifier: Programming Language :: Python :: 3
Classifier: Programming Language :: Python :: 3.3
License-File: LICENSE
License-File: AUTHORS.md
Requires-Dist: requests
Requires-Dist: requests-oauthlib>=0.4.1
Requires-Dist: python-dateutil
Requires-Dist: pytz
Dynamic: author
Dynamic: author-email
Dynamic: classifier
Dynamic: description
Dynamic: download-url
Dynamic: home-page
Dynamic: keywords
Dynamic: license
Dynamic: license-file
Dynamic: requires-dist
Dynamic: summary
